mimic_iv_analysis/__init__.py
mimic_iv_analysis/cli.py
mimic_iv_analysis/main_cli.py
mimic_iv_analysis/configurations/__init__.py
mimic_iv_analysis/configurations/config.yaml
mimic_iv_analysis/configurations/params.py
mimic_iv_analysis/configurations/settings.py
mimic_iv_analysis/core/__init__.py
mimic_iv_analysis/core/clustering.py
mimic_iv_analysis/core/dask_config.py
mimic_iv_analysis/core/feature_engineering.py
mimic_iv_analysis/core/filtering.py
mimic_iv_analysis/examples/__init__.py
mimic_iv_analysis/examples/exmples_data_loader.py
mimic_iv_analysis/io/__init__.py
mimic_iv_analysis/io/data_loader.ipynb
mimic_iv_analysis/io/data_loader.py
mimic_iv_analysis/io/temp.ipynb
mimic_iv_analysis/mimic_iv_analysis.egg-info/PKG-INFO
mimic_iv_analysis/mimic_iv_analysis.egg-info/SOURCES.txt
mimic_iv_analysis/mimic_iv_analysis.egg-info/dependency_links.txt
mimic_iv_analysis/mimic_iv_analysis.egg-info/not-zip-safe
mimic_iv_analysis/mimic_iv_analysis.egg-info/requires.txt
mimic_iv_analysis/mimic_iv_analysis.egg-info/top_level.txt
mimic_iv_analysis/visualization/__init__.py
mimic_iv_analysis/visualization/app.py
mimic_iv_analysis/visualization/visualizer_utils.py
mimic_iv_analysis/visualization/Obsolete/app_pyhealth.py
mimic_iv_analysis/visualization/Obsolete/app_pyhealth_refactored.py
mimic_iv_analysis/visualization/Obsolete/app_refactored_claude.py
mimic_iv_analysis/visualization/Obsolete/app_refactored_gemini.py
mimic_iv_analysis/visualization/Obsolete/app_works_before_refactoring.py
mimic_iv_analysis/visualization/app_components/__init__.py
mimic_iv_analysis/visualization/app_components/analysis_visualization_tab.py
mimic_iv_analysis/visualization/app_components/clustering_analysis_tab.py
mimic_iv_analysis/visualization/app_components/exploration_and_viz.py
mimic_iv_analysis/visualization/app_components/feature_engineering_tab.py
mimic_iv_analysis/visualization/app_components/filtering_tab.py
mimic_iv_analysis/visualization/app_components/sidebar.py
mimic_iv_analysis-1.13.1.dist-info/licenses/LICENSE.md
mimic_iv_analysis-1.13.1.dist-info/METADATA
mimic_iv_analysis-1.13.1.dist-info/WHEEL
mimic_iv_analysis-1.13.1.dist-info/entry_points.txt
mimic_iv_analysis-1.13.1.dist-info/top_level.txt
mimic_iv_analysis-1.13.1.dist-info/RECORD
