Metadata-Version: 2.4
Name: mimic_iv_analysis
Version: 1.13.1
Summary: A data science and machine learning framework for nursing research
Author-email: Artin Majdi <msm2024@gmail.com>
License: MIT
Project-URL: Homepage, https://github.com/artinmajdi/mimic_iv_analysis
Project-URL: Documentation, https://github.com/artinmajdi/mimic_iv_analysis/docs
Project-URL: Repository, https://github.com/artinmajdi/mimic_iv_analysis.git
Project-URL: Issues, https://github.com/artinmajdi/mimic_iv_analysis/issues
Keywords: nursing research,healthcare,AI,medical analysis
Classifier: Development Status :: 3 - Alpha
Classifier: Intended Audience :: Healthcare Industry
Classifier: Intended Audience :: Science/Research
Classifier: License :: OSI Approved :: MIT License
Classifier: Operating System :: OS Independent
Classifier: Programming Language :: Python :: 3
Classifier: Programming Language :: Python :: 3.10
Classifier: Programming Language :: Python :: 3.11
Classifier: Programming Language :: Python :: 3.12
Classifier: Topic :: Scientific/Engineering :: Medical Science Apps.
Classifier: Topic :: Scientific/Engineering :: Artificial Intelligence
Requires-Python: <3.13,>=3.10
License-File: LICENSE.md
Requires-Dist: numpy
Requires-Dist: pandas
Requires-Dist: dask[distributed]
Requires-Dist: pyarrow
Requires-Dist: scipy
Requires-Dist: scikit-learn
Requires-Dist: matplotlib
Requires-Dist: seaborn
Requires-Dist: plotly
Requires-Dist: streamlit
Requires-Dist: umap-learn
Requires-Dist: jupyter
Requires-Dist: ipywidgets
Requires-Dist: notebook
Requires-Dist: dask-labextension
Requires-Dist: tqdm
Requires-Dist: python-dotenv
Requires-Dist: pyyaml
Requires-Dist: joblib
Requires-Dist: watchdog
Requires-Dist: dotenv
Requires-Dist: humanize
Requires-Dist: pytest
Requires-Dist: sphinx
Requires-Dist: sphinx-rtd-theme
Requires-Dist: pydantic>=2.11.5
Requires-Dist: rich>=14.0.0
Requires-Dist: psutil>=7.0.0
Requires-Dist: pip>=23.0.0
Provides-Extra: dev
Requires-Dist: pytest>=6.0; extra == "dev"
Requires-Dist: pytest-cov>=2.0; extra == "dev"
Requires-Dist: black>=22.0; extra == "dev"
Requires-Dist: isort>=5.0; extra == "dev"
Requires-Dist: flake8>=3.9; extra == "dev"
Requires-Dist: mypy>=0.9; extra == "dev"
Requires-Dist: sphinx>=4.0; extra == "dev"
Requires-Dist: sphinx-rtd-theme>=1.0; extra == "dev"
Requires-Dist: twine>=6.0; extra == "dev"
Requires-Dist: wheel; extra == "dev"
Requires-Dist: build>=1.0; extra == "dev"
Provides-Extra: test
Requires-Dist: pytest>=6.0; extra == "test"
Requires-Dist: pytest-cov>=2.0; extra == "test"
Dynamic: license-file
